zipview/__init__.py
zipview/test_settings.py
zipview/views.py
django_zipview-2.0.0.dist-info/LICENSE
django_zipview-2.0.0.dist-info/METADATA
django_zipview-2.0.0.dist-info/WHEEL
django_zipview-2.0.0.dist-info/top_level.txt
django_zipview-2.0.0.dist-info/RECORD
