Metadata-Version: 2.1
Name: django-zipview
Version: 2.0.0
Summary: A simple Django base view to zip and stream several files.
Home-page: https://github.com/thibault/django-zipview/
Author: Thibault Jouannic
Author-email: thibault@miximum.fr
License: MIT License
Platform: UNKNOWN
Classifier: Environment :: Web Environment
Classifier: Framework :: Django
Classifier: Intended Audience :: Developers
Classifier: License :: OSI Approved :: MIT License
Classifier: Operating System :: OS Independent
Classifier: Programming Language :: Python
Classifier: Programming Language :: Python :: 3
Classifier: Topic :: Internet :: WWW/HTTP
Classifier: Topic :: Internet :: WWW/HTTP :: Dynamic Content
